LICENSE
README.md
setup.py
labelshift/__init__.py
labelshift/get_method.py
labelshift/lse.py
labelshift.egg-info/PKG-INFO
labelshift.egg-info/SOURCES.txt
labelshift.egg-info/dependency_links.txt
labelshift.egg-info/requires.txt
labelshift.egg-info/top_level.txt
labelshift/calibrations/__init__.py
labelshift/calibrations/base.py
labelshift/calibrations/bcts.py
labelshift/calibrations/ts.py
labelshift/datasets/__init__.py
labelshift/datasets/data_utils.py
labelshift/datasets/dataset.py
labelshift/datasets/dirichlet_dataset.py
labelshift/datasets/imbalanced_dataset.py
labelshift/datasets/transform.py
labelshift/methods/__init__.py
labelshift/methods/base.py
labelshift/methods/bbse.py
labelshift/methods/ensemble.py
labelshift/methods/mlls.py
labelshift/methods/rlls.py
labelshift/nets/__init__.py
labelshift/nets/utils.py
labelshift/nets/bert/__init__.py
labelshift/nets/bert/bert.py
labelshift/nets/hubert/__init__.py
labelshift/nets/hubert/hubert.py
labelshift/nets/resnet/__init__.py
labelshift/nets/resnet/resnet.py
labelshift/nets/vit/__init__.py
labelshift/nets/vit/vit.py
labelshift/nets/wave2vecv2/__init__.py
labelshift/nets/wave2vecv2/wave2vecv2.py
labelshift/nets/wrn/__init__.py
labelshift/nets/wrn/wrn.py
labelshift/nets/wrn/wrn_var.py
labelshift/trainer/__init__.py
labelshift/trainer/trainer.py
labelshift/trainer/trainer_utils.py
labelshift/utils/__init__.py
labelshift/utils/config.py
labelshift/utils/utils.py
tests/__init__.py
tests/test_lse.py
tests/datasets/__init__.py
tests/datasets/test_resample.py
tests/datasets/utils.py