Metadata-Version: 2.1
Name: labelshift
Version: 0.2.11
Summary: A pytorch-based toolbox for label shift estimation
Home-page: https://github.com/pm25/Label-Shift-Estimation
Author: Pin-Yen Huang
Author-email: pyhuang97@gmail.com
License: MIT
Keywords: pytorch label-shift-estimation
Requires-Python: >=3.7
License-File: LICENSE
